azure/mgmt/containerservicefleet/__init__.py
azure/mgmt/containerservicefleet/_configuration.py
azure/mgmt/containerservicefleet/_container_service_fleet_mgmt_client.py
azure/mgmt/containerservicefleet/_patch.py
azure/mgmt/containerservicefleet/_serialization.py
azure/mgmt/containerservicefleet/_version.py
azure/mgmt/containerservicefleet/py.typed
azure/mgmt/containerservicefleet/aio/__init__.py
azure/mgmt/containerservicefleet/aio/_configuration.py
azure/mgmt/containerservicefleet/aio/_container_service_fleet_mgmt_client.py
azure/mgmt/containerservicefleet/aio/_patch.py
azure/mgmt/containerservicefleet/aio/operations/__init__.py
azure/mgmt/containerservicefleet/aio/operations/_auto_upgrade_profile_operations_operations.py
azure/mgmt/containerservicefleet/aio/operations/_auto_upgrade_profiles_operations.py
azure/mgmt/containerservicefleet/aio/operations/_fleet_members_operations.py
azure/mgmt/containerservicefleet/aio/operations/_fleet_update_strategies_operations.py
azure/mgmt/containerservicefleet/aio/operations/_fleets_operations.py
azure/mgmt/containerservicefleet/aio/operations/_operations.py
azure/mgmt/containerservicefleet/aio/operations/_patch.py
azure/mgmt/containerservicefleet/aio/operations/_update_runs_operations.py
azure/mgmt/containerservicefleet/models/__init__.py
azure/mgmt/containerservicefleet/models/_container_service_fleet_mgmt_client_enums.py
azure/mgmt/containerservicefleet/models/_models_py3.py
azure/mgmt/containerservicefleet/models/_patch.py
azure/mgmt/containerservicefleet/operations/__init__.py
azure/mgmt/containerservicefleet/operations/_auto_upgrade_profile_operations_operations.py
azure/mgmt/containerservicefleet/operations/_auto_upgrade_profiles_operations.py
azure/mgmt/containerservicefleet/operations/_fleet_members_operations.py
azure/mgmt/containerservicefleet/operations/_fleet_update_strategies_operations.py
azure/mgmt/containerservicefleet/operations/_fleets_operations.py
azure/mgmt/containerservicefleet/operations/_operations.py
azure_mgmt_containerservicefleet-3.1.0.dist-info/LICENSE
azure_mgmt_containerservicefleet-3.1.0.dist-info/METADATA
azure_mgmt_containerservicefleet-3.1.0.dist-info/WHEEL
azure_mgmt_containerservicefleet-3.1.0.dist-info/top_level.txt
azure_mgmt_containerservicefleet-3.1.0.dist-info/RECORD
